mrl/__init__.py
mrl/_nbdev.py
mrl/chem.py
mrl/combichem.py
mrl/core.py
mrl/dataloaders.py
mrl/imports.py
mrl/layers.py
mrl/model_zoo.py
mrl/pharmacophore.py
mrl/policy_gradient.py
mrl/torch_core.py
mrl/torch_imports.py
mrl/vocab.py
mrl/g_models/__init__.py
mrl/g_models/all.py
mrl/g_models/generative_base.py
mrl/g_models/lstm_lm.py
mrl/g_models/vae.py
mrl/templates/__init__.py
mrl/templates/all.py
mrl/templates/blocks.py
mrl/templates/filters.py
mrl/templates/template.py
mrl/train/__init__.py
mrl/train/agent.py
mrl/train/all.py
mrl/train/buffer.py
mrl/train/callback.py
mrl/train/environment.py
mrl/train/log.py
mrl/train/loss.py
mrl/train/reward.py
mrl/train/sampler.py
mrl/train/template_cb.py
mrl_pypi-0.1.5.dist-info/LICENSE
mrl_pypi-0.1.5.dist-info/METADATA
mrl_pypi-0.1.5.dist-info/WHEEL
mrl_pypi-0.1.5.dist-info/top_level.txt
mrl_pypi-0.1.5.dist-info/RECORD
