Metadata-Version: 2.1
Name: mrl-pypi
Version: 0.1.5
Summary: Molecular reinforcement learning
Home-page: https://github.com/DarkMatterAI/mrl/tree/main/
Author: Karl Heyer
Author-email: karl@darkmatterai.co
License: MIT License
Keywords: machine learning,cheminformatics
Classifier: Development Status :: 5 - Production/Stable
Classifier: Intended Audience :: Developers
Classifier: Natural Language :: English
Classifier: Programming Language :: Python :: 3.7
Classifier: Programming Language :: Python :: 3.8
Classifier: License :: OSI Approved :: MIT License
Requires-Python: >=3.7
License-File: LICENSE
Requires-Dist: pandas
Requires-Dist: numpy
Requires-Dist: matplotlib
Requires-Dist: scipy
Requires-Dist: fastprogress
Requires-Dist: selfies (>=2.0.0)
Requires-Dist: scikit-learn
Requires-Dist: networkx
Requires-Dist: requests
Requires-Dist: numba
Requires-Dist: rdkit-pypi
Requires-Dist: torch (>=1.8.0)
